lmsystems/__init__.py
lmsystems/cli.py
lmsystems/client.py
lmsystems/config.py
lmsystems/custom_node.py
lmsystems/exceptions.py
lmsystems/purchased_graph.py
lmsystems-1.0.8.dist-info/LICENSE
lmsystems-1.0.8.dist-info/METADATA
lmsystems-1.0.8.dist-info/WHEEL
lmsystems-1.0.8.dist-info/entry_points.txt
lmsystems-1.0.8.dist-info/top_level.txt
lmsystems-1.0.8.dist-info/RECORD
