Metadata-Version: 2.1
Name: lmsystems
Version: 1.0.8
Summary: SDK for integrating purchased graphs from the lmsystems marketplace.
Home-page: https://docs.lmsystems.ai/
Author: Sean Sullivan
Author-email: sean.sullivan3@yahoo.com
Classifier: Programming Language :: Python :: 3
Classifier: Operating System :: OS Independent
License-File: LICENSE
Requires-Dist: requests (>=2.25.1)
Requires-Dist: langgraph (>=0.2.53)
Requires-Dist: langgraph-sdk (>=0.1.36)
Requires-Dist: langchain-core (>=0.3.31)
Requires-Dist: httpx (>=0.24.0)
Requires-Dist: pyjwt (>=2.0.0)
Requires-Dist: click (>=8.0.0)
